[{"bolum":"Kardiyoloji","doktorRandevulari":[],"TC":"11111111111","Ad":"Ahmet","Soyad":"Yılmaz","Sifre":"1234"},{"bolum":"Nöroloji","doktorRandevulari":[],"TC":"22222222222","Ad":"Ayşe","Soyad":"Kaya","Sifre":"1234"},{"bolum":"Ortopedi","doktorRandevulari":[],"TC":"33333333333","Ad":"Mehmet","Soyad":"Demir","Sifre":"1234"},{"bolum":"Pediatri","doktorRandevulari":[],"TC":"44444444444","Ad":"Fatma","Soyad":"Çelik","Sifre":"1234"},{"bolum":"Göz Hastalıkları","doktorRandevulari":[],"TC":"55555555555","Ad":"Ali","Soyad":"Şahin","Sifre":"1234"},{"bolum":"Dermatoloji","doktorRandevulari":[],"TC":"66666666666","Ad":"Zeynep","Soyad":"Arslan","Sifre":"1234"},{"bolum":"Dahiliye","doktorRandevulari":[],"TC":"77777777778","Ad":"Mustafa","Soyad":"Koç","Sifre":"1234"}]